django_enumfield/__init__.py
django_enumfield/enum.py
django_enumfield/exceptions.py
django_enumfield/models.py
django_enumfield/py.typed
django_enumfield/validators.py
django_enumfield/contrib/__init__.py
django_enumfield/contrib/drf.py
django_enumfield/db/__init__.py
django_enumfield/db/fields.py
django_enumfield/forms/__init__.py
django_enumfield/forms/fields.py
django_enumfield/tests/__init__.py
django_enumfield/tests/models.py
django_enumfield/tests/test_contrib.py
django_enumfield/tests/test_enum.py
django_enumfield/tests/test_settings.py
django_enumfield/tests/test_validators.py
django_enumfield/tests/urls.py
django_enumfield-3.1.dist-info/AUTHORS
django_enumfield-3.1.dist-info/LICENSE
django_enumfield-3.1.dist-info/METADATA
django_enumfield-3.1.dist-info/WHEEL
django_enumfield-3.1.dist-info/top_level.txt
django_enumfield-3.1.dist-info/RECORD
