Metadata-Version: 2.1
Name: django-enumfield
Version: 3.1
Summary: Custom Django field for using enumerations of named constants
Home-page: http://github.com/5monkeys/django-enumfield
Download-URL: https://github.com/5monkeys/django-enumfield/tarball/3.1
Author: Hannes Ljungberg
Author-email: hannes@5monkeys.se
License: MIT
Keywords: django,enum,field,status,state,choices,form,model
Platform: any
Classifier: Programming Language :: Python
Classifier: Programming Language :: Python :: 3
Classifier: Programming Language :: Python :: 3.7
Classifier: Programming Language :: Python :: 3.8
Classifier: Programming Language :: Python :: 3.9
Classifier: Programming Language :: Python :: 3.10
Classifier: Programming Language :: Python :: 3.11
Classifier: Framework :: Django
Classifier: Natural Language :: English
Classifier: Environment :: Web Environment
Classifier: Intended Audience :: Developers
Classifier: License :: OSI Approved :: MIT License
Classifier: Operating System :: OS Independent
Classifier: Topic :: Utilities
Classifier: Topic :: Software Development :: Libraries :: Python Modules
Provides-Extra: dev
License-File: LICENSE
License-File: AUTHORS
